{
  "timeline": [
    {
      "id": 695590992658412444,
      "date": "2025-09-22",
      "title": "_chat.txt",
      "description": "Category: correspondence/messages",
      "priority": "medium",
      "type": "archived"
    },
    {
      "id": -1798582703867777018,
      "date": "2025-09-22",
      "title": "_chat.txt",
      "description": "Category: correspondence/messages",
      "priority": "medium",
      "type": "archived"
    },
    {
      "id": -6592351829874780349,
      "date": "2025-09-22",
      "title": "_chat.txt",
      "description": "Category: correspondence/messages",
      "priority": "medium",
      "type": "archived"
    },
    {
      "id": 379168959190149163,
      "date": "2025-09-22",
      "title": "_chat.txt",
      "description": "Category: correspondence/messages",
      "priority": "medium",
      "type": "archived"
    },
    {
      "id": 1230902099525035471,
      "date": "2025-09-26",
      "title": "conversations.txt",
      "description": "Category: correspondence/messages",
      "priority": "medium",
      "type": "archived"
    },
    {
      "id": -1082133737981021586,
      "date": "2025-09-26",
      "title": "conversations.txt",
      "description": "Category: correspondence/messages",
      "priority": "medium",
      "type": "archived"
    },
    {
      "id": 7636891828764165436,
      "date": "2025-09-26",
      "title": "conversations.txt",
      "description": "Category: correspondence/messages",
      "priority": "medium",
      "type": "archived"
    },
    {
      "id": 7581984497717652148,
      "date": "2025-09-26",
      "title": "conversations.txt",
      "description": "Category: correspondence/messages",
      "priority": "medium",
      "type": "archived"
    },
    {
      "id": -5960080038794575494,
      "date": "2025-09-26",
      "title": "Sole caregiver.gsheet",
      "description": "Category: evidence/supporting_documents",
      "priority": "low",
      "type": "archived"
    },
    {
      "id": -1614573205494772715,
      "date": "2025-09-26",
      "title": "Sole caregiver.gsheet",
      "description": "Category: evidence/supporting_documents",
      "priority": "low",
      "type": "archived"
    },
    {
      "id": 3560902634659301384,
      "date": "2025-09-26",
      "title": "Sole caregiver.gsheet",
      "description": "Category: evidence/supporting_documents",
      "priority": "low",
      "type": "archived"
    },
    {
      "id": 4025047826748250232,
      "date": "2025-09-26",
      "title": "Sole caregiver.gsheet",
      "description": "Category: evidence/supporting_documents",
      "priority": "low",
      "type": "archived"
    },
    {
      "id": -6862427497752046162,
      "date": "2025-09-26",
      "title": "Communications.rtf",
      "description": "Category: correspondence/emails",
      "priority": "medium",
      "type": "archived"
    },
    {
      "id": 3211274672401862225,
      "date": "2025-09-26",
      "title": "Communications.rtf",
      "description": "Category: correspondence/emails",
      "priority": "medium",
      "type": "archived"
    },
    {
      "id": -6247836436293684573,
      "date": "2025-09-26",
      "title": "Communications.rtf",
      "description": "Category: correspondence/emails",
      "priority": "medium",
      "type": "archived"
    },
    {
      "id": 7009571986130423511,
      "date": "2025-09-26",
      "title": "Communications.rtf",
      "description": "Category: correspondence/emails",
      "priority": "medium",
      "type": "archived"
    },
    {
      "id": 9030125225359334570,
      "date": "2025-09-26",
      "title": "@history.docx",
      "description": "Category: correspondence/messages",
      "priority": "medium",
      "type": "archived"
    },
    {
      "id": -5772662640116356817,
      "date": "2025-09-26",
      "title": "@history.docx",
      "description": "Category: correspondence/messages",
      "priority": "medium",
      "type": "archived"
    },
    {
      "id": -5978940536586684011,
      "date": "2025-09-26",
      "title": "@history.docx",
      "description": "Category: correspondence/messages",
      "priority": "medium",
      "type": "archived"
    },
    {
      "id": -3825112180964517561,
      "date": "2025-09-26",
      "title": "@history.docx",
      "description": "Category: correspondence/messages",
      "priority": "medium",
      "type": "archived"
    }
  ],
  "evidence": [
    {
      "id": -5960080038794575494,
      "title": "Sole caregiver.gsheet",
      "type": "supporting_documents",
      "description": "Keywords: caregiver, sole",
      "relevance": "low",
      "dateAdded": "2025-09-26"
    },
    {
      "id": -1614573205494772715,
      "title": "Sole caregiver.gsheet",
      "type": "supporting_documents",
      "description": "Keywords: caregiver, sole",
      "relevance": "low",
      "dateAdded": "2025-09-26"
    },
    {
      "id": 3560902634659301384,
      "title": "Sole caregiver.gsheet",
      "type": "supporting_documents",
      "description": "Keywords: caregiver, sole",
      "relevance": "low",
      "dateAdded": "2025-09-26"
    },
    {
      "id": 4025047826748250232,
      "title": "Sole caregiver.gsheet",
      "type": "supporting_documents",
      "description": "Keywords: caregiver, sole",
      "relevance": "low",
      "dateAdded": "2025-09-26"
    },
    {
      "id": 1230902099525035471,
      "title": "conversations.txt",
      "type": "messages",
      "description": "Keywords: ",
      "relevance": "medium",
      "dateAdded": "2025-09-26"
    },
    {
      "id": 9030125225359334570,
      "title": "@history.docx",
      "type": "messages",
      "description": "Keywords: ",
      "relevance": "medium",
      "dateAdded": "2025-09-26"
    },
    {
      "id": 695590992658412444,
      "title": "_chat.txt",
      "type": "messages",
      "description": "Keywords: ",
      "relevance": "medium",
      "dateAdded": "2025-09-22"
    },
    {
      "id": -5772662640116356817,
      "title": "@history.docx",
      "type": "messages",
      "description": "Keywords: ",
      "relevance": "medium",
      "dateAdded": "2025-09-26"
    },
    {
      "id": -5978940536586684011,
      "title": "@history.docx",
      "type": "messages",
      "description": "Keywords: ",
      "relevance": "medium",
      "dateAdded": "2025-09-26"
    },
    {
      "id": -3825112180964517561,
      "title": "@history.docx",
      "type": "messages",
      "description": "Keywords: ",
      "relevance": "medium",
      "dateAdded": "2025-09-26"
    },
    {
      "id": -1082133737981021586,
      "title": "conversations.txt",
      "type": "messages",
      "description": "Keywords: ",
      "relevance": "medium",
      "dateAdded": "2025-09-26"
    },
    {
      "id": 7636891828764165436,
      "title": "conversations.txt",
      "type": "messages",
      "description": "Keywords: ",
      "relevance": "medium",
      "dateAdded": "2025-09-26"
    },
    {
      "id": -1798582703867777018,
      "title": "_chat.txt",
      "type": "messages",
      "description": "Keywords: ",
      "relevance": "medium",
      "dateAdded": "2025-09-22"
    },
    {
      "id": 7581984497717652148,
      "title": "conversations.txt",
      "type": "messages",
      "description": "Keywords: ",
      "relevance": "medium",
      "dateAdded": "2025-09-26"
    },
    {
      "id": -6592351829874780349,
      "title": "_chat.txt",
      "type": "messages",
      "description": "Keywords: ",
      "relevance": "medium",
      "dateAdded": "2025-09-22"
    },
    {
      "id": 379168959190149163,
      "title": "_chat.txt",
      "type": "messages",
      "description": "Keywords: ",
      "relevance": "medium",
      "dateAdded": "2025-09-22"
    },
    {
      "id": -6862427497752046162,
      "title": "Communications.rtf",
      "type": "emails",
      "description": "Keywords: ",
      "relevance": "medium",
      "dateAdded": "2025-09-26"
    },
    {
      "id": 3211274672401862225,
      "title": "Communications.rtf",
      "type": "emails",
      "description": "Keywords: ",
      "relevance": "medium",
      "dateAdded": "2025-09-26"
    },
    {
      "id": -6247836436293684573,
      "title": "Communications.rtf",
      "type": "emails",
      "description": "Keywords: ",
      "relevance": "medium",
      "dateAdded": "2025-09-26"
    },
    {
      "id": 7009571986130423511,
      "title": "Communications.rtf",
      "type": "emails",
      "description": "Keywords: ",
      "relevance": "medium",
      "dateAdded": "2025-09-26"
    }
  ],
  "correspondence": [],
  "strategy": {
    "case_strength_score": 100,
    "total_evidence_files": 20,
    "high_priority_evidence": 0,
    "evidence_categories": 3
  }
}